mutwo/mmml_converters/__init__.py
mutwo/mmml_converters/backends.py
mutwo/mmml_converters/codes.py
mutwo/mmml_converters/configurations.py
mutwo/mmml_converters/constants.py
mutwo/mmml_converters/frontends.py
mutwo/mmml_utilities/__init__.py
mutwo/mmml_utilities/codes.py
mutwo/mmml_utilities/exceptions.py
mutwo/mmml_version/__init__.py
mutwo_mmml-0.10.0.dist-info/licenses/LICENSE
mutwo_mmml-0.10.0.dist-info/METADATA
mutwo_mmml-0.10.0.dist-info/WHEEL
mutwo_mmml-0.10.0.dist-info/top_level.txt
mutwo_mmml-0.10.0.dist-info/RECORD
