Metadata-Version: 2.4
Name: mutwo.mmml
Version: 0.10.0
Summary: MMML extension for event based framework for generative art
Home-page: https://github.com/mutwo-org/mutwo.ext
Author: Levin Eric Zimmermann
Author-email: levin.eric.zimmermann@posteo.eu
License: GPL
Project-URL: Documentation, https://mutwo-org.github.io/
Requires-Python: >=3.10, <4
License-File: LICENSE
Requires-Dist: mutwo.core<3.0.0,>=2.0.0
Requires-Dist: mutwo.music<1.0.0,>=0.27.0
Requires-Dist: chevron<1.0.0,>=0.13.1
Provides-Extra: testing
Requires-Dist: pytest>=7.1.1; extra == "testing"
Dynamic: author
Dynamic: author-email
Dynamic: description
Dynamic: description-content-type
Dynamic: home-page
Dynamic: license
Dynamic: license-file
Dynamic: project-url
Dynamic: provides-extra
Dynamic: requires-dist
Dynamic: requires-python
Dynamic: summary
